pystddic/__init__.py
pystddic/main.py
pystddic-0.0.5.dist-info/LICENSE
pystddic-0.0.5.dist-info/METADATA
pystddic-0.0.5.dist-info/WHEEL
pystddic-0.0.5.dist-info/top_level.txt
pystddic-0.0.5.dist-info/RECORD
