Metadata-Version: 2.1
Name: pystddic
Version: 0.0.5
Summary: Standard Dictionary Management(Korean Ver)
Home-page: https://github.com/oh-seung/pystddic
Author: oh seung
Author-email: seung.oh17@gmail.com
Requires-Python: >=3.8
License-File: LICENSE
Requires-Dist: pandas (>=1.3)
Requires-Dist: numpy (>=1.20)
Requires-Dist: psutil (>=5.8)
Requires-Dist: ray (>=1.12)
Requires-Dist: tqdm (>=4.62)
